<?xml version="1.0"?>
<SaveDataCalib xmlns:xsi="http://www.w3.org/2001/XMLSchema-instance" xmlns:xsd="http://www.w3.org/2001/XMLSchema" xmlns="Save Calibration Settings">
  <Items>
    <ManualCalibConfig>
      <IsGroup>true</IsGroup>
      <IsCollapsed>false</IsCollapsed>
      <IECid>0</IECid>
      <RENid>99</RENid>
      <ItemName>Common</ItemName>
      <ReadValue />
      <WriteValue />
      <MinValue />
      <MaxValue />
      <Unit />
      <RowPosition>0</RowPosition>
    </ManualCalibConfig>
    <ManualCalibConfig>
      <IsGroup>false</IsGroup>
      <IsCollapsed>false</IsCollapsed>
      <IECid>FS</IECid>
      <RENid>14</RENid>
      <ItemName>Sampling Frequency</ItemName>
      <ReadValue />
      <WriteValue />
      <MinValue>1200</MinValue>
      <MaxValue>4000</MaxValue>
      <Unit>Hz</Unit>
      <RowPosition>0</RowPosition>
    </ManualCalibConfig>
    <ManualCalibConfig>
      <IsGroup>false</IsGroup>
      <IsCollapsed>false</IsCollapsed>
      <IECid>U</IECid>
      <RENid>1</RENid>
      <ItemName>Meter constant</ItemName>
      <ReadValue />
      <WriteValue />
      <MinValue />
      <MaxValue />
      <Unit />
      <RowPosition>2</RowPosition>
    </ManualCalibConfig>
    <ManualCalibConfig>
      <IsGroup>false</IsGroup>
      <IsCollapsed>false</IsCollapsed>
      <IECid>U</IECid>
      <RENid>68</RENid>
      <ItemName>Meter Phase constant</ItemName>
      <ReadValue />
      <WriteValue />
      <MinValue />
      <MaxValue />
      <Unit />
      <RowPosition>1</RowPosition>
    </ManualCalibConfig>
    <ManualCalibConfig>
      <IsGroup>false</IsGroup>
      <IsCollapsed>false</IsCollapsed>
      <IECid>U</IECid>
      <RENid>69</RENid>
      <ItemName>Timer Offset</ItemName>
      <ReadValue />
      <WriteValue />
      <MinValue />
      <MaxValue />
      <Unit />
      <RowPosition>1</RowPosition>
    </ManualCalibConfig>
    <ManualCalibConfig>
      <IsGroup>true</IsGroup>
      <IsCollapsed>false</IsCollapsed>
      <IECid>0</IECid>
      <RENid>0</RENid>
      <ItemName>Line 1</ItemName>
      <ReadValue />
      <WriteValue />
      <MinValue />
      <MaxValue />
      <Unit />
      <RowPosition>0</RowPosition>
    </ManualCalibConfig>
    <ManualCalibConfig>
      <IsGroup>false</IsGroup>
      <IsCollapsed>false</IsCollapsed>
      <IECid>VO</IECid>
      <RENid>18</RENid>
      <ItemName>Voltage Coeff (P1)</ItemName>
      <ReadValue>23.3</ReadValue>
      <WriteValue>23.30</WriteValue>
      <MinValue>0.1</MinValue>
      <MaxValue />
      <Unit />
      <RowPosition>6</RowPosition>
    </ManualCalibConfig>
    <ManualCalibConfig>
      <IsGroup>false</IsGroup>
      <IsCollapsed>false</IsCollapsed>
      <IECid>CN</IECid>
      <RENid>19</RENid>
      <ItemName>Current Coeff (P1)</ItemName>
      <ReadValue>48794.19</ReadValue>
      <WriteValue>48794.19</WriteValue>
      <MinValue>0.1</MinValue>
      <MaxValue />
      <Unit />
      <RowPosition>7</RowPosition>
    </ManualCalibConfig>
    <ManualCalibConfig>
      <IsGroup>false</IsGroup>
      <IsCollapsed>false</IsCollapsed>
      <IECid>VO</IECid>
      <RENid>21</RENid>
      <ItemName>Active Power Coeff (P1)</ItemName>
      <ReadValue>1136904</ReadValue>
      <WriteValue>1136904</WriteValue>
      <MinValue>0.1</MinValue>
      <MaxValue />
      <Unit />
      <RowPosition>8</RowPosition>
    </ManualCalibConfig>
    <ManualCalibConfig>
      <IsGroup>false</IsGroup>
      <IsCollapsed>false</IsCollapsed>
      <IECid>VO</IECid>
      <RENid>22</RENid>
      <ItemName>Reactive Power Coeff (P1)</ItemName>
      <ReadValue>1143469</ReadValue>
      <WriteValue>1143469</WriteValue>
      <MinValue>0.1</MinValue>
      <MaxValue />
      <Unit />
      <RowPosition>9</RowPosition>
    </ManualCalibConfig>
    <ManualCalibConfig>
      <IsGroup>false</IsGroup>
      <IsCollapsed>false</IsCollapsed>
      <IECid>VO</IECid>
      <RENid>23</RENid>
      <ItemName>Apparent Power Coeff (P1)</ItemName>
      <ReadValue>1136904</ReadValue>
      <WriteValue>1136904</WriteValue>
      <MinValue>0.1</MinValue>
      <MaxValue />
      <Unit />
      <RowPosition>10</RowPosition>
    </ManualCalibConfig>
    <ManualCalibConfig>
      <IsGroup>false</IsGroup>
      <IsCollapsed>false</IsCollapsed>
      <IECid>VO</IECid>
      <RENid>24</RENid>
      <ItemName>Phase Shift(P1)</ItemName>
      <ReadValue>-2.115543</ReadValue>
      <WriteValue>-4.8</WriteValue>
      <MinValue>-180</MinValue>
      <MaxValue>180</MaxValue>
      <Unit />
      <RowPosition>11</RowPosition>
    </ManualCalibConfig>
    <ManualCalibConfig>
      <IsGroup>false</IsGroup>
      <IsCollapsed>false</IsCollapsed>
      <IECid>VO</IECid>
      <RENid>26</RENid>
      <ItemName>ADC Gain (P1)</ItemName>
      <ReadValue>1</ReadValue>
      <WriteValue />
      <MinValue>0.1</MinValue>
      <MaxValue />
      <Unit />
      <RowPosition>5</RowPosition>
    </ManualCalibConfig>
    <ManualCalibConfig>
      <IsGroup>false</IsGroup>
      <IsCollapsed>false</IsCollapsed>
      <IECid>VO</IECid>
      <RENid>28</RENid>
      <ItemName>Voltage Offset (P1)</ItemName>
      <ReadValue>18326</ReadValue>
      <WriteValue />
      <MinValue>0.1</MinValue>
      <MaxValue />
      <Unit />
      <RowPosition>13</RowPosition>
    </ManualCalibConfig>
    <ManualCalibConfig>
      <IsGroup>true</IsGroup>
      <IsCollapsed>false</IsCollapsed>
      <IECid>0</IECid>
      <RENid>0</RENid>
      <ItemName>Line 2</ItemName>
      <ReadValue />
      <WriteValue />
      <MinValue />
      <MaxValue />
      <Unit />
      <RowPosition>0</RowPosition>
    </ManualCalibConfig>
    <ManualCalibConfig>
      <IsGroup>false</IsGroup>
      <IsCollapsed>false</IsCollapsed>
      <IECid>VO</IECid>
      <RENid>34</RENid>
      <ItemName>Voltage Coeff (P2)</ItemName>
      <ReadValue />
      <WriteValue />
      <MinValue>0.1</MinValue>
      <MaxValue />
      <Unit />
      <RowPosition>0</RowPosition>
    </ManualCalibConfig>
    <ManualCalibConfig>
      <IsGroup>false</IsGroup>
      <IsCollapsed>false</IsCollapsed>
      <IECid>CN</IECid>
      <RENid>35</RENid>
      <ItemName>Current Coeff (P2)</ItemName>
      <ReadValue />
      <WriteValue />
      <MinValue>0.1</MinValue>
      <MaxValue />
      <Unit />
      <RowPosition>0</RowPosition>
    </ManualCalibConfig>
    <ManualCalibConfig>
      <IsGroup>false</IsGroup>
      <IsCollapsed>false</IsCollapsed>
      <IECid>VO</IECid>
      <RENid>37</RENid>
      <ItemName>Active Power Coeff (P2)</ItemName>
      <ReadValue />
      <WriteValue />
      <MinValue>0.1</MinValue>
      <MaxValue />
      <Unit />
      <RowPosition>5</RowPosition>
    </ManualCalibConfig>
    <ManualCalibConfig>
      <IsGroup>false</IsGroup>
      <IsCollapsed>false</IsCollapsed>
      <IECid>VO</IECid>
      <RENid>38</RENid>
      <ItemName>Reactive Power Coeff (P2)</ItemName>
      <ReadValue />
      <WriteValue />
      <MinValue>0.1</MinValue>
      <MaxValue />
      <Unit />
      <RowPosition>5</RowPosition>
    </ManualCalibConfig>
    <ManualCalibConfig>
      <IsGroup>false</IsGroup>
      <IsCollapsed>false</IsCollapsed>
      <IECid>VO</IECid>
      <RENid>39</RENid>
      <ItemName>Apparent Power Coeff (P2)</ItemName>
      <ReadValue />
      <WriteValue />
      <MinValue>0.1</MinValue>
      <MaxValue />
      <Unit />
      <RowPosition>5</RowPosition>
    </ManualCalibConfig>
    <ManualCalibConfig>
      <IsGroup>false</IsGroup>
      <IsCollapsed>false</IsCollapsed>
      <IECid>VO</IECid>
      <RENid>40</RENid>
      <ItemName>Phase Shift(P2)</ItemName>
      <ReadValue />
      <WriteValue />
      <MinValue>-180</MinValue>
      <MaxValue>180</MaxValue>
      <Unit />
      <RowPosition>5</RowPosition>
    </ManualCalibConfig>
    <ManualCalibConfig>
      <IsGroup>false</IsGroup>
      <IsCollapsed>false</IsCollapsed>
      <IECid>VO</IECid>
      <RENid>42</RENid>
      <ItemName>ADC Gain (P2)</ItemName>
      <ReadValue />
      <WriteValue />
      <MinValue>0.1</MinValue>
      <MaxValue />
      <Unit />
      <RowPosition>5</RowPosition>
    </ManualCalibConfig>
    <ManualCalibConfig>
      <IsGroup>false</IsGroup>
      <IsCollapsed>false</IsCollapsed>
      <IECid>VO</IECid>
      <RENid>44</RENid>
      <ItemName>Voltage Offset (P2)</ItemName>
      <ReadValue />
      <WriteValue />
      <MinValue>0.1</MinValue>
      <MaxValue />
      <Unit />
      <RowPosition>5</RowPosition>
    </ManualCalibConfig>
    <ManualCalibConfig>
      <IsGroup>true</IsGroup>
      <IsCollapsed>false</IsCollapsed>
      <IECid>0</IECid>
      <RENid>0</RENid>
      <ItemName>Line 3</ItemName>
      <ReadValue />
      <WriteValue />
      <MinValue />
      <MaxValue />
      <Unit />
      <RowPosition>0</RowPosition>
    </ManualCalibConfig>
    <ManualCalibConfig>
      <IsGroup>false</IsGroup>
      <IsCollapsed>false</IsCollapsed>
      <IECid>VO</IECid>
      <RENid>50</RENid>
      <ItemName>Voltage Coeff (P3)</ItemName>
      <ReadValue />
      <WriteValue />
      <MinValue>0.1</MinValue>
      <MaxValue />
      <Unit />
      <RowPosition>11</RowPosition>
    </ManualCalibConfig>
    <ManualCalibConfig>
      <IsGroup>false</IsGroup>
      <IsCollapsed>false</IsCollapsed>
      <IECid>CN</IECid>
      <RENid>51</RENid>
      <ItemName>Current Coeff (P3)</ItemName>
      <ReadValue />
      <WriteValue />
      <MinValue>0.1</MinValue>
      <MaxValue />
      <Unit />
      <RowPosition>12</RowPosition>
    </ManualCalibConfig>
    <ManualCalibConfig>
      <IsGroup>false</IsGroup>
      <IsCollapsed>false</IsCollapsed>
      <IECid>VO</IECid>
      <RENid>53</RENid>
      <ItemName>Active Power Coeff (P3)</ItemName>
      <ReadValue />
      <WriteValue />
      <MinValue>0.1</MinValue>
      <MaxValue />
      <Unit />
      <RowPosition>5</RowPosition>
    </ManualCalibConfig>
    <ManualCalibConfig>
      <IsGroup>false</IsGroup>
      <IsCollapsed>false</IsCollapsed>
      <IECid>VO</IECid>
      <RENid>54</RENid>
      <ItemName>Reactive Power Coeff (P3)</ItemName>
      <ReadValue />
      <WriteValue />
      <MinValue>0.1</MinValue>
      <MaxValue />
      <Unit />
      <RowPosition>5</RowPosition>
    </ManualCalibConfig>
    <ManualCalibConfig>
      <IsGroup>false</IsGroup>
      <IsCollapsed>false</IsCollapsed>
      <IECid>VO</IECid>
      <RENid>55</RENid>
      <ItemName>Apparent Power Coeff (P3)</ItemName>
      <ReadValue />
      <WriteValue />
      <MinValue>0.1</MinValue>
      <MaxValue />
      <Unit />
      <RowPosition>5</RowPosition>
    </ManualCalibConfig>
    <ManualCalibConfig>
      <IsGroup>false</IsGroup>
      <IsCollapsed>false</IsCollapsed>
      <IECid>VO</IECid>
      <RENid>56</RENid>
      <ItemName>Phase Shift(P3)</ItemName>
      <ReadValue />
      <WriteValue />
      <MinValue>-180</MinValue>
      <MaxValue>180</MaxValue>
      <Unit />
      <RowPosition>5</RowPosition>
    </ManualCalibConfig>
    <ManualCalibConfig>
      <IsGroup>false</IsGroup>
      <IsCollapsed>false</IsCollapsed>
      <IECid>VO</IECid>
      <RENid>58</RENid>
      <ItemName>ADC Gain (P3)</ItemName>
      <ReadValue />
      <WriteValue />
      <MinValue>0.1</MinValue>
      <MaxValue />
      <Unit />
      <RowPosition>5</RowPosition>
    </ManualCalibConfig>
    <ManualCalibConfig>
      <IsGroup>false</IsGroup>
      <IsCollapsed>false</IsCollapsed>
      <IECid>VO</IECid>
      <RENid>60</RENid>
      <ItemName>Voltage Offset (P3)</ItemName>
      <ReadValue />
      <WriteValue />
      <MinValue>0.1</MinValue>
      <MaxValue />
      <Unit />
      <RowPosition>5</RowPosition>
    </ManualCalibConfig>
    <ManualCalibConfig>
      <IsGroup>true</IsGroup>
      <IsCollapsed>false</IsCollapsed>
      <IECid>0</IECid>
      <RENid>0</RENid>
      <ItemName>Neutral line</ItemName>
      <ReadValue />
      <WriteValue />
      <MinValue />
      <MaxValue />
      <Unit />
      <RowPosition>0</RowPosition>
    </ManualCalibConfig>
    <ManualCalibConfig>
      <IsGroup>false</IsGroup>
      <IsCollapsed>false</IsCollapsed>
      <IECid>CN</IECid>
      <RENid>4</RENid>
      <ItemName>Current N.Coeff</ItemName>
      <ReadValue />
      <WriteValue />
      <MinValue>0.1</MinValue>
      <MaxValue />
      <Unit />
      <RowPosition>15</RowPosition>
    </ManualCalibConfig>
    <ManualCalibConfig>
      <IsGroup>true</IsGroup>
      <IsCollapsed>false</IsCollapsed>
      <IECid>0</IECid>
      <RENid>0</RENid>
      <ItemName>Miscellaneous</ItemName>
      <ReadValue />
      <WriteValue />
      <MinValue />
      <MaxValue />
      <Unit />
      <RowPosition>0</RowPosition>
    </ManualCalibConfig>
    <ManualCalibConfig>
      <IsGroup>false</IsGroup>
      <IsCollapsed>false</IsCollapsed>
      <IECid>RKWH</IECid>
      <RENid>97</RENid>
      <ItemName>Flag to clear KWh counter</ItemName>
      <ReadValue />
      <WriteValue />
      <MinValue>0</MinValue>
      <MaxValue />
      <Unit />
      <RowPosition>0</RowPosition>
    </ManualCalibConfig>
    <ManualCalibConfig>
      <IsGroup>false</IsGroup>
      <IsCollapsed>false</IsCollapsed>
      <IECid>RKVARH</IECid>
      <RENid>98</RENid>
      <ItemName>Flag to clear KARh counter</ItemName>
      <ReadValue />
      <WriteValue />
      <MinValue>0</MinValue>
      <MaxValue />
      <Unit />
      <RowPosition>0</RowPosition>
    </ManualCalibConfig>
    <ManualCalibConfig>
      <IsGroup>false</IsGroup>
      <IsCollapsed>false</IsCollapsed>
      <IECid>RKVAH</IECid>
      <RENid>99</RENid>
      <ItemName>Flag to clear KVAh counter</ItemName>
      <ReadValue />
      <WriteValue />
      <MinValue>0</MinValue>
      <MaxValue />
      <Unit />
      <RowPosition>0</RowPosition>
    </ManualCalibConfig>
    <ManualCalibConfig>
      <IsGroup>false</IsGroup>
      <IsCollapsed>false</IsCollapsed>
      <IECid>RMDWH</IECid>
      <RENid>100</RENid>
      <ItemName>Flag to clear KWh max demand counter</ItemName>
      <ReadValue />
      <WriteValue />
      <MinValue>0</MinValue>
      <MaxValue />
      <Unit />
      <RowPosition>0</RowPosition>
    </ManualCalibConfig>
    <ManualCalibConfig>
      <IsGroup>false</IsGroup>
      <IsCollapsed>false</IsCollapsed>
      <IECid>RMDVARH</IECid>
      <RENid>101</RENid>
      <ItemName>Flag to clear KVARh max demand counter</ItemName>
      <ReadValue />
      <WriteValue />
      <MinValue>0</MinValue>
      <MaxValue />
      <Unit />
      <RowPosition>0</RowPosition>
    </ManualCalibConfig>
    <ManualCalibConfig>
      <IsGroup>false</IsGroup>
      <IsCollapsed>false</IsCollapsed>
      <IECid>RMDVAH</IECid>
      <RENid>102</RENid>
      <ItemName>Flag to clear KVAh max demand counter</ItemName>
      <ReadValue />
      <WriteValue />
      <MinValue>0</MinValue>
      <MaxValue />
      <Unit />
      <RowPosition>0</RowPosition>
    </ManualCalibConfig>
    <ManualCalibConfig>
      <IsGroup>false</IsGroup>
      <IsCollapsed>false</IsCollapsed>
      <IECid>RTMPR</IECid>
      <RENid>103</RENid>
      <ItemName>Flag to clear all tamper records</ItemName>
      <ReadValue />
      <WriteValue />
      <MinValue>0</MinValue>
      <MaxValue />
      <Unit />
      <RowPosition>0</RowPosition>
    </ManualCalibConfig>
    <ManualCalibConfig>
      <IsGroup>false</IsGroup>
      <IsCollapsed>false</IsCollapsed>
      <IECid>RENGYLOG</IECid>
      <RENid>104</RENid>
      <ItemName>Flag to clear all energy log records</ItemName>
      <ReadValue />
      <WriteValue />
      <MinValue>0</MinValue>
      <MaxValue />
      <Unit />
      <RowPosition>0</RowPosition>
    </ManualCalibConfig>
  </Items>
</SaveDataCalib>